{
  "employees": [
      {
          "id": 1,
          "date": "00/00/0000",
          "name": "Brennan Bradley",
          "function": "dock"
      },
      {
          "id": 2,
          "date": "00/00/0000",
          "name": "Brennan Bradley",
          "function": "stow"
      },
      {
          "id": 3,
          "date": "00/00/0000",
          "name": "Brennan Bradley",
          "function": "pa"
      },
      {
          "id": 4,
          "date": "00/00/0000",
          "name": "Brennan Bradley",
          "function": "laborshare"
      },
      {
          "id": 5,
          "date": "00/00/0000",
          "name": "Brennan Bradley",
          "function": "unloader"
      },
      {
          "id": 6,
          "date": "00/00/0000",
          "name": "Brennan Bradley",
          "function": "problem solve"
      }
  ]
}
